phylox/__init__.py
phylox/constants.py
phylox/dinetwork.py
phylox/newick_parser.py
phylox/cherrypicking/Heuristic_Main_UserFriendly.py
phylox/cherrypicking/__init__.py
phylox/cherrypicking/base.py
phylox/cherrypicking/best_subnetwork.py
phylox/cherrypicking/combining_networks.py
phylox/cherrypicking/tree_child_sequences.py
phylox/classes/__init__.py
phylox/classes/dinetwork.py
phylox/classes/networkclass.py
phylox/exceptions/__init__.py
phylox/exceptions/invalidmovedefinitionexception.py
phylox/exceptions/invalidmoveexception.py
phylox/exceptions/nosolutionexception.py
phylox/exceptions/timeoutexception.py
phylox/generators/__init__.py
phylox/generators/heath/__init__.py
phylox/generators/heath/heath.py
phylox/generators/heath/heath_cli.py
phylox/generators/lgt/__init__.py
phylox/generators/lgt/base.py
phylox/generators/mcmc/__init__.py
phylox/generators/mcmc/base.py
phylox/generators/randomTC/__init__.py
phylox/generators/randomTC/random_tc_network.py
phylox/generators/trees/__init__.py
phylox/generators/trees/add_edges.py
phylox/generators/trees/beta_splitting_tree.py
phylox/generators/trees/well_known.py
phylox/generators/zods/__init__.py
phylox/generators/zods/zods.py
phylox/generators/zods/zods_cli.py
phylox/isomorphism/__init__.py
phylox/isomorphism/base.py
phylox/networkproperties/__init__.py
phylox/networkproperties/properties.py
phylox/rearrangement/__init__.py
phylox/rearrangement/invertsequence.py
phylox/rearrangement/movability.py
phylox/rearrangement/move.py
phylox/rearrangement/movetype.py
phylox/rearrangement/rearrangementproblem.py
phylox/rearrangement/exact_distance/__init__.py
phylox/rearrangement/exact_distance/base.py
phylox/rearrangement/heuristics/__init__.py
phylox/rearrangement/heuristics/cli_main.py
phylox/rearrangement/heuristics/green_line_heuristic.py
phylox/rearrangement/heuristics/red_line_heuristic.py
phylox/rearrangement/heuristics/utils.py
phylox-1.1.2.dist-info/licenses/LICENSE
phylox-1.1.2.dist-info/METADATA
phylox-1.1.2.dist-info/WHEEL
phylox-1.1.2.dist-info/entry_points.txt
phylox-1.1.2.dist-info/top_level.txt
phylox-1.1.2.dist-info/RECORD
