Metadata-Version: 2.4
Name: phylox
Version: 1.1.2
Summary: A package with tools for constructing, manipulating, and analyzing phylogenetic networks.
Author-email: Remie Janssen <remiejanssen92@gmail.com>
Project-URL: Homepage, https://github.com/RemieJanssen/PhyloX
Project-URL: Bug Tracker, https://github.com/RemieJanssen/PhyloX/issues
Classifier: Programming Language :: Python :: 3
Classifier: License :: OSI Approved :: MIT License
Classifier: Operating System :: OS Independent
Requires-Python: >=3.7
License-File: LICENSE
Requires-Dist: networkx>=2.6
Requires-Dist: numpy>=1.21.6
Requires-Dist: scipy>=1.7.3
Requires-Dist: matplotlib>=3.5
Dynamic: license-file
